geographiclib/__init__.py
geographiclib/accumulator.py
geographiclib/constants.py
geographiclib/geodesic.py
geographiclib/geodesiccapability.py
geographiclib/geodesicline.py
geographiclib/geomath.py
geographiclib/polygonarea.py
geographiclib/test/__init__.py
geographiclib/test/test_geodesic.py
geographiclib-1.52.dist-info/LICENSE
geographiclib-1.52.dist-info/METADATA
geographiclib-1.52.dist-info/WHEEL
geographiclib-1.52.dist-info/top_level.txt
geographiclib-1.52.dist-info/RECORD
